{
  "auth": {
    "year4project2e3abc74": {
      "service": "Cognito",
      "providerPlugin": "awscloudformation",
      "dependsOn": [],
      "customAuth": false
    }
  },
  "api": {
    "year4project": {
      "service": "AppSync",
      "providerPlugin": "awscloudformation",
      "output": {
        "authConfig": {
          "defaultAuthentication": {
            "authenticationType": "AMAZON_COGNITO_USER_POOLS",
            "userPoolConfig": {
              "userPoolId": "authyear4project2e3abc74"
            }
          },
          "additionalAuthenticationProviders": []
        }
      }
    }
  },
  "hosting": {
    "amplifyhosting": {
      "service": "amplifyhosting",
      "type": "cicd",
      "lastPushTimeStamp": "2021-04-13T14:07:03.799Z"
    }
  }
}